paxplot/__init__.py
paxplot/core.py
paxplot/datasets.py
paxplot/data/hydroclimate_model_evaluation.csv
paxplot/data/tradeoff.csv
paxplot-0.1.4b2.dist-info/LICENSE
paxplot-0.1.4b2.dist-info/METADATA
paxplot-0.1.4b2.dist-info/WHEEL
paxplot-0.1.4b2.dist-info/top_level.txt
paxplot-0.1.4b2.dist-info/RECORD
