Metadata-Version: 2.1
Name: paxplot
Version: 0.1.4b2
Summary: Paxplot is a Python visualization library for parallel coordinate plots based on Matplotlib.
Home-page: https://github.com/kravitsjacob/paxplot
Author: Jacob Kravits
Author-email: kravitsjacob@gmail.com
Project-URL: Bug Tracker, https://github.com/kravitsjacob/paxplot/issues
Classifier: Programming Language :: Python :: 3
Classifier: License :: OSI Approved :: MIT License
Classifier: Operating System :: OS Independent
Requires-Python: >=3.7
License-File: LICENSE
Requires-Dist: matplotlib (>=3.5)
